{
  "project_info": {
    "project_number": "735244278201",
    "firebase_url": "https://food-delivery-1574214974139.firebaseio.com",
    "project_id": "food-delivery-1574214974139",
    "storage_bucket": "food-delivery-1574214974139.appspot.com"
  },
  "client": [
    {
      "client_info": {
        "mobilesdk_app_id": "1:735244278201:android:8a8fcca6da962921737e68",
        "android_client_info": {
          "package_name": "com.customerapp"
        }
      },
      "oauth_client": [
        {
          "client_id": "735244278201-7essu65l62ka6fb6cgb2r24vkfqbldc1.apps.googleusercontent.com",
          "client_type": 1,
          "android_info": {
            "package_name": "com.customerapp",
            "certificate_hash": "6f178f27357c7df97249d39e5b212be49918a8e1"
          }
        },
        {
          "client_id": "735244278201-t38mmu28glk5ht5aqbevqpqihsbpqtih.apps.googleusercontent.com",
          "client_type": 3
        }
      ],
      "api_key": [
        {
          "current_key": "AIzaSyDeq8A70d-_6hRaOHi1zxAZT5TF8Gk4V5M"
        }
      ],
      "services": {
        "appinvite_service": {
          "other_platform_oauth_client": [
            {
              "client_id": "735244278201-t38mmu28glk5ht5aqbevqpqihsbpqtih.apps.googleusercontent.com",
              "client_type": 3
            }
          ]
        }
      }
    }
  ],
  "configuration_version": "1"
}